hippycampus/__init__.py
hippycampus/__main__.py
hippycampus/cli.py
hippycampus/langchain_util.py
hippycampus/mcp_server.py
hippycampus/openapi_builder.py
hippycampus/spec_parser.py
iflow_mcp_cromwellian_hippycampus-0.1.1.dist-info/METADATA
iflow_mcp_cromwellian_hippycampus-0.1.1.dist-info/WHEEL
iflow_mcp_cromwellian_hippycampus-0.1.1.dist-info/entry_points.txt
iflow_mcp_cromwellian_hippycampus-0.1.1.dist-info/licenses/LICENSE.md
iflow_mcp_cromwellian_hippycampus-0.1.1.dist-info/RECORD
