Metadata-Version: 2.4
Name: iflow-mcp_cromwellian_hippycampus
Version: 0.1.1
Summary: 
License-File: LICENSE.md
Author: Ray Cromwell
Author-email: cromwellian@gmail.com
Requires-Python: >=3.11
Classifier: Programming Language :: Python :: 3
Classifier: Programming Language :: Python :: 3.11
Classifier: Programming Language :: Python :: 3.12
Classifier: Programming Language :: Python :: 3.13
Classifier: Programming Language :: Python :: 3.14
Requires-Dist: httpx (>=0.28.1)
Requires-Dist: langchain (>=0.3.18)
Requires-Dist: langchain-google-genai (>=2.0.0)
Requires-Dist: langchain-openai (>=0.3.6)
Requires-Dist: mcp[cli] (>=1.3.0)
Requires-Dist: pydantic (>=2.10.6)
Requires-Dist: requests (>=2.32.3)
Requires-Dist: rich (>=13.9.4)
